MANIFEST.in
README.rst
setup.py
se3/__init__.py
se3/homtrans3d.py
se3/plotT.py
se3/rot3d.py
se3/se3.py
se3.egg-info/PKG-INFO
se3.egg-info/SOURCES.txt
se3.egg-info/dependency_links.txt
se3.egg-info/not-zip-safe
se3.egg-info/requires.txt
se3.egg-info/top_level.txt