Metadata-Version: 1.1
Name: se3
Version: 0.2
Summary: Homogenous transforms in special euclidian 3-space.
Home-page: https://github.com/ccorcos/se3
Author: Chet Corcos
Author-email: ccorcos@gmail
License: MIT
Keywords: euclidian special homogenous transform rotation 3d
Platform: UNKNOWN
Classifier: Development Status :: 2 - Pre-Alpha
Classifier: Programming Language :: Python :: 2.7
Classifier: Intended Audience :: Science/Research
